flask_pushjack/__init__.py
flask_pushjack/__meta__.py
Flask_Pushjack-1.0.0.dist-info/top_level.txt
Flask_Pushjack-1.0.0.dist-info/METADATA
Flask_Pushjack-1.0.0.dist-info/DESCRIPTION.rst
Flask_Pushjack-1.0.0.dist-info/metadata.json
Flask_Pushjack-1.0.0.dist-info/WHEEL
Flask_Pushjack-1.0.0.dist-info/RECORD
