Metadata-Version: 1.1
Name: Flask-Pushjack
Version: 1.0.0
Summary: Flask extension for push notifications on APNS (iOS) and GCM (Android).
Home-page: https://github.com/dgilland/flask-pushjack
Author: Derrick Gilland
Author-email: dgilland@gmail.com
License: MIT License
Keywords: apns ios gcm android push notifications
Platform: UNKNOWN
Classifier: Development Status :: 3 - Alpha
Classifier: Intended Audience :: Developers
Classifier: Operating System :: OS Independent
Classifier: Programming Language :: Python
Classifier: License :: OSI Approved :: MIT License
Classifier: Topic :: Communications
Classifier: Topic :: Internet
Classifier: Topic :: Software Development :: Libraries :: Python Modules
Classifier: Topic :: Utilities
Classifier: Programming Language :: Python
Classifier: Programming Language :: Python :: 2
Classifier: Programming Language :: Python :: 2.6
Classifier: Programming Language :: Python :: 2.7
Classifier: Programming Language :: Python :: 3
Classifier: Programming Language :: Python :: 3.2
Classifier: Programming Language :: Python :: 3.3
Classifier: Programming Language :: Python :: 3.4
